src/__init__.py
src/main.py
src/inter_cli/__about__.py
src/inter_cli/__init__.py
src/inter_cli/config/__init__.py
src/inter_cli/config/config.py
src/inter_cli/decorators/__init__.py
src/inter_cli/decorators/singleton.py
src/inter_cli/exceptions/__init__.py
src/inter_cli/exceptions/invalid_mlops_config.py
src/inter_cli/exceptions/unsupported_functionality_exception.py
src/inter_cli/frameworks/__init__.py
src/inter_cli/frameworks/typer/__init__.py
src/inter_cli/frameworks/typer/cli.py
src/inter_cli/functionalities/__init__.py
src/inter_cli/functionalities/base_functionality.py
src/inter_cli/functionalities/factory.py
src/inter_cli/functionalities/v1/__init__.py
src/inter_cli/functionalities/v1/online_deployment.py
src/inter_cli/functionalities/v1/project_initializer.py
src/inter_cli/functionalities/v1/lib/common.py
src/inter_cli/functionalities/v1/schemas/__init__.py
src/inter_cli/functionalities/v1/schemas/deployment/__init__.py
src/inter_cli/functionalities/v1/schemas/deployment/enums.py
src/inter_cli/functionalities/v1/schemas/deployment/mlops_config.py
src/inter_cli/functionalities/v1/schemas/deployment/online_deployment/online_deployment_spec.py
src/inter_cli/lib/common.py
src/inter_cli/lib/helpers/__init__.py
src/inter_cli/lib/helpers/git_helper.py
src/inter_cli/lib/helpers/gitlab_helper.py
src/inter_cli/lib/helpers/jinja_helper.py
src/inter_cli/schemas/env.py
src/inter_cli/schemas/resources.py
src/inter_cli/templates/v1/cookiecutter/cookiecutter.json
src/inter_cli/templates/v1/cookiecutter/{{cookiecutter.project_name}}/Dockerfile
src/inter_cli/templates/v1/cookiecutter/{{cookiecutter.project_name}}/README.md
src/inter_cli/templates/v1/cookiecutter/{{cookiecutter.project_name}}/mlops-config.yaml
src/inter_cli/templates/v1/cookiecutter/{{cookiecutter.project_name}}/src/__init__.py
src/inter_cli/templates/v1/cookiecutter/{{cookiecutter.project_name}}/src/api/main.py
src/inter_cli/templates/v1/cookiecutter/{{cookiecutter.project_name}}/src/api/requirements.txt
inter_cli-1.1.dist-info/METADATA
inter_cli-1.1.dist-info/WHEEL
inter_cli-1.1.dist-info/entry_points.txt
inter_cli-1.1.dist-info/licenses/LICENSE.txt
inter_cli-1.1.dist-info/RECORD
